README.md
setup.py
opbeat_django/__init__.py
opbeat_django/admin.py
opbeat_django/api.py
opbeat_django/apps.py
opbeat_django/conf.py
opbeat_django/models.py
opbeat_django/tests.py
opbeat_django/views.py
opbeat_django.egg-info/PKG-INFO
opbeat_django.egg-info/SOURCES.txt
opbeat_django.egg-info/dependency_links.txt
opbeat_django.egg-info/not-zip-safe
opbeat_django.egg-info/requires.txt
opbeat_django.egg-info/top_level.txt
opbeat_django/management/__init__.py
opbeat_django/management/commands/__init__.py
opbeat_django/management/commands/opbeat_release.py
opbeat_django/migrations/__init__.py